odoo/addons/sale_stock_picking_validation_blocking/README.rst
odoo/addons/sale_stock_picking_validation_blocking/__init__.py
odoo/addons/sale_stock_picking_validation_blocking/__manifest__.py
odoo/addons/sale_stock_picking_validation_blocking/i18n/sale_stock_picking_validation_blocking.pot
odoo/addons/sale_stock_picking_validation_blocking/models/__init__.py
odoo/addons/sale_stock_picking_validation_blocking/models/sale_order.py
odoo/addons/sale_stock_picking_validation_blocking/models/stock_picking.py
odoo/addons/sale_stock_picking_validation_blocking/readme/CONTRIBUTORS.rst
odoo/addons/sale_stock_picking_validation_blocking/readme/DESCRIPTION.rst
odoo/addons/sale_stock_picking_validation_blocking/readme/USAGE.rst
odoo/addons/sale_stock_picking_validation_blocking/static/description/icon.png
odoo/addons/sale_stock_picking_validation_blocking/static/description/index.html
odoo/addons/sale_stock_picking_validation_blocking/tests/__init__.py
odoo/addons/sale_stock_picking_validation_blocking/tests/test_sale_stock.py
odoo/addons/sale_stock_picking_validation_blocking/views/sale_order.xml
odoo/addons/sale_stock_picking_validation_blocking/views/stock_picking.xml
odoo13_addon_sale_stock_picking_validation_blocking-13.0.1.0.1.dist-info/METADATA
odoo13_addon_sale_stock_picking_validation_blocking-13.0.1.0.1.dist-info/WHEEL
odoo13_addon_sale_stock_picking_validation_blocking-13.0.1.0.1.dist-info/top_level.txt
odoo13_addon_sale_stock_picking_validation_blocking-13.0.1.0.1.dist-info/RECORD
